[
  {
    "participantID": "116",
    "instanceName": "BU5",
    "seqBall": 1,
    "urnPosteriors": [
      48.0,
      52.0
    ],
    "colourPosteriors": [
      35.0,
      15.0,
      15.0,
      35.0
    ],
    "responseTimeUrn": 13.0664063,
    "responseTimeColour": 82.53369
  },
  {
    "participantID": "116",
    "instanceName": "BU5",
    "seqBall": 2,
    "urnPosteriors": [
      32.0,
      68.0
    ],
    "colourPosteriors": [
      10.0,
      21.0,
      21.0,
      48.0
    ],
    "responseTimeUrn": 19.3330078,
    "responseTimeColour": 52.53369
  },
  {
    "participantID": "116",
    "instanceName": "BU5",
    "seqBall": 3,
    "urnPosteriors": [
      15.0,
      85.0
    ],
    "colourPosteriors": [
      3.0,
      21.0,
      21.0,
      55.0
    ],
    "responseTimeUrn": 8.016602,
    "responseTimeColour": 33.7666
  }
]